karmakaze/__init__.py
karmakaze/_main.py
karmakaze-3.0.1.dist-info/LICENSE
karmakaze-3.0.1.dist-info/METADATA
karmakaze-3.0.1.dist-info/WHEEL
karmakaze-3.0.1.dist-info/RECORD
